genessir/__init__.py
genessir/__main__.py
genessir/abc.py
genessir/activity.py
genessir/appinfo.py
genessir/asset.py
genessir/audit_logs.py
genessir/backoff.py
genessir/calls.py
genessir/channel.py
genessir/client.py
genessir/colour.py
genessir/context_managers.py
genessir/context_properties.py
genessir/embeds.py
genessir/emoji.py
genessir/enums.py
genessir/errors.py
genessir/file.py
genessir/flags.py
genessir/gateway.py
genessir/guild.py
genessir/guild_folder.py
genessir/http.py
genessir/integrations.py
genessir/invite.py
genessir/iterators.py
genessir/member.py
genessir/mentions.py
genessir/message.py
genessir/mixins.py
genessir/object.py
genessir/oggparse.py
genessir/opus.py
genessir/partial_emoji.py
genessir/permissions.py
genessir/player.py
genessir/raw_models.py
genessir/reaction.py
genessir/relationship.py
genessir/role.py
genessir/settings.py
genessir/state.py
genessir/sticker.py
genessir/team.py
genessir/template.py
genessir/user.py
genessir/utils.py
genessir/voice_client.py
genessir/webhook.py
genessir/widget.py
genessir/accounts/__init__.py
genessir/accounts/account.py
genessir/accounts/gateway.py
genessir/accounts/http.py
genessir/accounts/user.py
genessir/ext/commands/__init__.py
genessir/ext/commands/_types.py
genessir/ext/commands/bot.py
genessir/ext/commands/cog.py
genessir/ext/commands/context.py
genessir/ext/commands/converter.py
genessir/ext/commands/cooldowns.py
genessir/ext/commands/core.py
genessir/ext/commands/errors.py
genessir/ext/commands/help.py
genessir/ext/commands/view.py
genessir/ext/tasks/__init__.py
genessir.py-1.0.1.dist-info/LICENSE
genessir.py-1.0.1.dist-info/METADATA
genessir.py-1.0.1.dist-info/WHEEL
genessir.py-1.0.1.dist-info/top_level.txt
genessir.py-1.0.1.dist-info/RECORD
