Metadata-Version: 2.1
Name: genessir.py
Version: 1.0.1
Summary: A Python wrapper for the Discord API
Home-page: https://github.com/dolfies/discord.py-self
Author: Genessir
License: MIT
Project-URL: Documentation, https://dolf.ml/discord.py-self
Project-URL: Issue tracker, https://github.com/dolfies/discord.py-self/issues
Platform: UNKNOWN
Classifier: Development Status :: 5 - Production/Stable
Classifier: License :: OSI Approved :: MIT License
Classifier: Intended Audience :: Developers
Classifier: Natural Language :: English
Classifier: Operating System :: OS Independent
Classifier: Programming Language :: Python :: 3.5
Classifier: Programming Language :: Python :: 3.6
Classifier: Programming Language :: Python :: 3.7
Classifier: Programming Language :: Python :: 3.8
Classifier: Topic :: Internet
Classifier: Topic :: Software Development :: Libraries
Classifier: Topic :: Software Development :: Libraries :: Python Modules
Classifier: Topic :: Utilities
Requires-Python: >=3.8
Requires-Dist: aiohttp (<3.8.0,>=3.6.0)
Provides-Extra: docs
Requires-Dist: sphinx (==3.0.3) ; extra == 'docs'
Requires-Dist: sphinxcontrib-trio (==1.1.2) ; extra == 'docs'
Requires-Dist: sphinxcontrib-websupport ; extra == 'docs'
Provides-Extra: voice
Requires-Dist: PyNaCl (<1.5,>=1.3.0) ; extra == 'voice'
